modelzoo/__init__.py
modelzoo/__version__.py
modelzoo/_delete.py
modelzoo/_info.py
modelzoo/_list.py
modelzoo/_logs.py
modelzoo/_predict.py
modelzoo/_start.py
modelzoo/_stop.py
modelzoo/_wait.py
modelzoo/api.py
modelzoo/deploy_lib.py
modelzoo/exceptions.py
modelzoo/model_state.py
modelzoo/resources_config.py
modelzoo/util.py
modelzoo/cli/__init__.py
modelzoo/config/__init__.py
modelzoo/fastai/__init__.py
modelzoo/fastai/_deploy.py
modelzoo/fastai/_predict.py
modelzoo/sklearn/__init__.py
modelzoo/sklearn/_deploy.py
modelzoo/sklearn/_predict.py
modelzoo/tensorflow/__init__.py
modelzoo/tensorflow/_deploy.py
modelzoo/tensorflow/_predict.py
modelzoo/tensorflow/util.py
modelzoo/torch/__init__.py
modelzoo/torch/_deploy.py
modelzoo/torch/_predict.py
modelzoo/torch/util.py
modelzoo/transformers/__init__.py
modelzoo/transformers/_deploy.py
modelzoo/transformers/_predict.py
modelzoo/transformers/util.py
tests/__init__.py
tests/mock_api_server.py
tests/test_auth.py
tests/fastai/__init__.py
tests/fastai/test_fastai.py
tests/tensorflow/__init__.py
tests/tensorflow/test_tensorflow.py
tests/tensorflow/test_util.py
tests/transformers/__init__.py
tests/transformers/test_transformers.py
modelzoo_client-0.15.0.dist-info/LICENSE
modelzoo_client-0.15.0.dist-info/METADATA
modelzoo_client-0.15.0.dist-info/WHEEL
modelzoo_client-0.15.0.dist-info/entry_points.txt
modelzoo_client-0.15.0.dist-info/top_level.txt
modelzoo_client-0.15.0.dist-info/RECORD
